{
  "no": 1425,
  "name": "刈安山森林自然公園",
  "kana": "かりやすやましんりんしぜんこうえん",
  "area": "あわら・坂井・福井,あわら市",
  "category": "自然・公園,山・川・湖",
  "lat": "36.226219",
  "lng": "136.328515",
  "zoom": "16",
  "url": "https://www.fuku-e.com/spot/detail_1425.html",
  "image": "https://www.fuku-e.com/lsc/upfile/spot/0000/1425/1425_1_l.jpg",
  "description": "ドライブウェイ・ハイキングコース・展望台などが整備されています。バードウォッチングや、ブナの純林をはじめとした豊かな緑の中での森林浴など、自然を満喫できます。",
  "電話番号": "あわら市観光振興課 0776-73-8029",
  "住所": "福井県あわら市清滝",
  "定休日": "11月上旬～4月初旬の間、公衆便所は冬季閉鎖します。",
  "アクセス": "JR芦原温泉駅から車で35分/北陸自動車道金津ICから車で35分",
  "ウェブサイト": "http://www.city.awara.lg.jp/mokuteki/industry/kanko/sizen/p000261.html"
}