{
  "id": "detail_1107",
  "name": "宝円寺",
  "kana": "ほうえんじ",
  "area": "丹南,越前市",
  "category": "歴史・文化・史跡,寺社仏閣",
  "lat": "35.89459",
  "lng": "136.158734",
  "zoom": "16",
  "url": "https://www.fuku-e.com/spot/detail_1107.html",
  "image": "https://www.fuku-e.com/lsc/upfile/spot/0000/1107/1107_1_l.jpg",
  "description": "加賀藩初代藩主前田利家が保護した寺。墓地には利家の両親の供養塔があります。利家と武生のつながりは、北陸の一向一揆勢力を鎮圧した織田信長が、武生を中心とした地域を前田利家、佐々成政、不破光治の府中三人衆に治めさせたことに始まります。その後、…",
  "電話番号": "宝円寺　 0778-22-1645",
  "住所": "福井県越前市高瀬1-27-4",
  "アクセス": "JR武生駅から徒歩20分/北陸自動車道武生ICから車で15分"
}