{
  "id": "detail_1668",
  "name": "旬菜食祭 花月楼",
  "kana": "しゅんさいしょくさい　かげつろう",
  "area": "永平寺町・奥越,勝山市",
  "category": "歴史・文化・史跡",
  "lat": "36.0605483388222",
  "lng": "136.49717688560486",
  "zoom": "17",
  "url": "https://www.fuku-e.com/spot/detail_1668.html",
  "image": "https://www.fuku-e.com/lsc/upfile/spot/0000/1668/1668_1_l.jpg",
  "description": "明治30年築の文化財「旧料亭花月楼」をリノベーション。かつて花街として栄えた風情ある建物です。1階は郷土料理を楽しめるランチや、和テイストのカフェメニューを楽しめるお食事処。日本の四季を感じるお庭を眺めながら、おくつろぎいただけます。2階の傘…",
  "電話番号": "0779-87-1355",
  "住所": "福井県勝山市本町2-6-21",
  "営業時間": "1階　カフェ　11時～14時00分(13時30分最終受付)\r\n2階　お座敷　11時～14時、18時～21時（要予約）",
  "定休日": "毎週火・水曜日、年末年始\r\n（火曜日は予約のみ）",
  "アクセス": "中部縦貫自動車道勝山ＩＣから車で約10分\r\nえちぜん鉄道勝山駅から徒歩で約10分",
  "駐車場": "あり",
  "駐車場：台数": "15台",
  "駐車場：大型バスの駐車": "2台",
  "ウェブサイト": "[旬菜食祭お食事処 花月楼](https://katsuyama-navi.jp/kagetsuro/)"
}