{
  "id": "detail_1435",
  "name": "みどりと自然の村「太陽広場」",
  "kana": "みどりとしぜんのむらたいようひろば",
  "area": "丹南,越前市",
  "category": "",
  "lat": "35.920399",
  "lng": "136.0809",
  "zoom": "16",
  "url": "https://www.fuku-e.com/spot/detail_1435.html",
  "image": "https://www.fuku-e.com/common/images/ogImg.png",
  "description": "どこまでも広がる緑の芝生に寝ころがったり、かけっこしたり、小さな子どもづれでも安心して遊べるスペースです。ランニングコースや照明設備つきテニスコートをはじめローラースケート場などが充実しています。キャンプ場もあり、アウトドアライフをしっか…",
  "電話番号": "事務所　0778-28-1119",
  "住所": "福井県越前市安養寺町5-3",
  "定休日": "毎週月曜(祝日除く)、国民の祝日の翌日、年末年始",
  "アクセス": "JR武生駅から車で15分/北陸自動車道武生ICから車で25分"
}