{
  "id": "detail_1494",
  "name": "解雷ヶ清水",
  "kana": "けらがしょうず",
  "area": "丹南,越前市",
  "category": "",
  "lat": "35.8874984546876",
  "lng": "136.025679843903",
  "zoom": "17",
  "url": "https://www.fuku-e.com/spot/detail_1494.html",
  "image": "https://www.fuku-e.com/lsc/upfile/spot/0000/1494/1494_1_l.jpg",
  "description": "解雷ヶ清水は干ばつでも枯れることがない霊水として親しまれています。今から1400年前、朝鮮半島から越前に渡ってきた百済の王女が神仏に念じたところ、雨が降りだし落雷の響きとともに岩間から清水が湧き出たという伝承が残っています。",
  "電話番号": "越前市環境政策課　0778-22-5342",
  "住所": "福井県越前市千合谷町",
  "アクセス": "JR武生駅から車で20分/北陸自動車道武生ICから車で30分"
}