{
  "id": "detail_1648",
  "name": "道の駅　恐竜渓谷かつやま",
  "kana": "みちのえききょうりゅうけいこくかつやま",
  "area": "永平寺町・奥越,勝山市",
  "category": "恐竜,道の駅・観光案内所等,道の駅,観光案内所,お土産店・商業施設,レンタサイクル",
  "lat": "36.072004",
  "lng": "136.478772",
  "zoom": "17",
  "url": "https://www.fuku-e.com/spot/detail_1648.html",
  "image": "https://www.fuku-e.com/lsc/upfile/spot/0000/1648/1648_1_l.jpg",
  "description": "令和2年6月20日オープン！■カフェレストラン　黒糖とこし餡をオリジナル配合してスッキリとした甘味に仕上げた「水ようかんソフトクリーム」、若狭牛で作るメンチカツを挟む「ラプトルバーガー」は、リッチな食感と香り、あふれる肉汁が自慢です！■ショップ…",
  "電話番号": "道の駅　恐竜渓谷かつやま\r\nTEL  0779-89-2234　FAX 0779-89-2235\r\n",
  "住所": "福井県勝山市荒土町松ヶ崎1-17",
  "営業時間": "ショップ/9:00～17:00(時期によって変動あり)\r\nレストラン/11:00～15:00(時期によって変動あり)",
  "定休日": "第２・第３火曜日",
  "アクセス": "中部縦貫自動車道勝山IC下車後、市内方面へ車で約1分",
  "駐車場": "あり",
  "駐車場：台数": "88",
  "駐車場：大型バスの駐車": "11",
  "ウェブサイト": "[道の駅　恐竜渓谷かつやまホームページ](http://katsuyama-navi.jp/michieki/)"
}