{
  "id": "detail_5166",
  "name": "五色山公園",
  "kana": "ごしきやまこうえん",
  "area": "若狭路,高浜町",
  "category": "自然・公園,山・川・湖,花",
  "lat": "35.52850673280158",
  "lng": "135.47781944274902",
  "zoom": "15",
  "url": "https://www.fuku-e.com/spot/detail_5166.html",
  "image": "https://www.fuku-e.com/lsc/upfile/spot/0000/5166/5166_1_l.jpg",
  "description": "約30万平方メートルの広大な敷地内に7000本ものサクラや500本のボタン、ツツジなどの季節ごとに色鮮やかな花々が楽しめます。",
  "電話番号": "0770-76-1641（五色山公園事務所(匠の美術館)）",
  "住所": "福井県高浜町山中64-3-1",
  "営業時間": "9:00～16:00",
  "定休日": "月曜から金曜日（祝日を除く）\r\n※12月～3月末は冬季休館",
  "アクセス": "JR若狭高浜駅から車で30分\r\n舞鶴若狭自動車道舞鶴東ICから車で50分"
}