{
  "id": "detail_1088",
  "name": "大成寺",
  "kana": "だいじょうじ",
  "area": "若狭路,高浜町",
  "category": "歴史・文化・史跡,寺社仏閣",
  "lat": "35.481641",
  "lng": "135.509927",
  "zoom": "16",
  "url": "https://www.fuku-e.com/spot/detail_1088.html",
  "image": "https://www.fuku-e.com/lsc/upfile/spot/0000/1088/1088_1_l.jpg",
  "description": "若狭でも数少ない臨済宗建仁寺派の中本山で、若狭三十三か所観音霊場巡礼31番札所です。心をリフレッシュしてくれる座禅体験も行っており、住職が説法と座禅を指導します。",
  "電話番号": "大成寺 0770-72-3089",
  "住所": "福井県高浜町日置(ひき)31-3",
  "料金": "無料",
  "アクセス": "JR青郷駅から徒歩17分/舞鶴若狭自動車道大飯高浜ICから車で15分",
  "駐車場": "あり",
  "駐車場：台数": "10",
  "ウェブサイト": "http://daijoji.net/"
}