{
  "id": "detail_1164",
  "name": "エルガイアおおい",
  "kana": "えるがいあおおい",
  "area": "若狭路,おおい町",
  "category": "歴史・文化・史跡",
  "lat": "35.480146",
  "lng": "135.629621",
  "zoom": "16",
  "url": "https://www.fuku-e.com/spot/detail_1164.html",
  "image": "https://www.fuku-e.com/lsc/upfile/spot/0000/1164/1164_1_l.jpg",
  "description": "「遊び、学び、発見！　エネルギーの未来と地球の未来」 世界最大級のバーチャル映像シアターや、松本零士さん監修の宇宙発電所アトラクション、そしてエネルギーのいまを紹介するパネル展示。3ゾーンを通じて、楽しみながら学び、考え、発見できるミュージ…",
  "電話番号": "エルガイアおおい 0770-77-2144",
  "住所": "福井県おおい町成海1-2",
  "営業時間": "9:00～17:00",
  "定休日": "月曜日(祝日の場合は翌平日)、年末年始(12月29日～1月3日)",
  "料金": "無料",
  "アクセス": "JR若狭本郷駅から車で5分、徒歩15分/舞鶴若狭自動車道小浜西ICから5分、大飯高浜ICから15分",
  "ウェブサイト": "http://www1.kepco.co.jp/pr/elgaia/"
}